README.md
setup.py
tunas2dsdl_c/__init__.py
tunas2dsdl_c/__version__.py
tunas2dsdl_c/cli.py
tunas2dsdl_c/dsdl_yaml_script.py
tunas2dsdl_c.egg-info/PKG-INFO
tunas2dsdl_c.egg-info/SOURCES.txt
tunas2dsdl_c.egg-info/dependency_links.txt
tunas2dsdl_c.egg-info/entry_points.txt
tunas2dsdl_c.egg-info/requires.txt
tunas2dsdl_c.egg-info/top_level.txt