Metadata-Version: 2.1
Name: tunas2dsdl-c
Version: 1.0.1
Summary: Python SDK for Converting Tunas Format Dataset to DSDL YAML
Author: DSDL team
Author-email: jiangyiying@pjlab.org.cn
Classifier: Programming Language :: Python :: 3.8
Classifier: Programming Language :: Python :: 3.9
Classifier: Programming Language :: Python :: 3.10
Requires-Python: >=3.8
